<?xml version="1.0"?>
<!DOCTYPE hibernate-mapping PUBLIC "-//Hibernate/Hibernate Mapping DTD 3.0//EN"
"http://hibernate.sourceforge.net/hibernate-mapping-3.0.dtd">
<!-- 
    Mapping file autogenerated by MyEclipse - Hibernate Tools
-->
<hibernate-mapping default-cascade="save-update">
    <class name="org.nescent.heliconius.hibernate.Individual" table="individual" schema="public">
        <id name="individualId" type="java.lang.Integer">
            <column name="individual_id" />
<generator class="sequence">
<param name="sequence">individual_individual_id_seq</param>
</generator>
        </id>
        <many-to-one name="stock" class="org.nescent.heliconius.hibernate.Stock" fetch="select">
            <column name="stock_id" />
        </many-to-one>
        <many-to-one name="organism" class="org.nescent.heliconius.hibernate.Organism" fetch="select">
            <column name="host_organism_id" />
        </many-to-one>
        <many-to-one name="cvterm" class="org.nescent.heliconius.hibernate.Cvterm" fetch="select">
            <column name="gender_id" />
        </many-to-one>
        <many-to-one name="crossexperiment" class="org.nescent.heliconius.hibernate.Crossexperiment" fetch="select">
            <column name="crossexperiment_id" />
        </many-to-one>
        <many-to-one name="contact" class="org.nescent.heliconius.hibernate.Contact" fetch="select">
            <column name="experimenter_id" />
        </many-to-one>
        <many-to-one name="geolocation" class="org.nescent.heliconius.hibernate.Geolocation" fetch="select">
            <column name="geolocation_id" />
        </many-to-one>
        <property name="name" type="java.lang.String">
            <column name="name" not-null="true" unique="true" />
        </property>
        <property name="description" type="java.lang.String">
            <column name="description" />
        </property>
        <property name="isCaptivityReared" type="java.lang.Boolean">
            <column name="is_captivity_reared" not-null="true" />
        </property>
        <property name="collectionDate" type="java.util.Date">
            <column name="collection_date" length="13" />
        </property>
        <set name="individualPhenotypes" inverse="true">
            <key>
                <column name="individual_id" not-null="true" />
            </key>
            <one-to-many class="org.nescent.heliconius.hibernate.IndividualPhenotype" />
        </set>
        <set name="individualBiotypes" inverse="true">
            <key>
                <column name="individual_id" not-null="true" />
            </key>
            <one-to-many class="org.nescent.heliconius.hibernate.IndividualBiotype" />
        </set>
        <set name="crossexperimentsForMaleId" inverse="true">
            <key>
                <column name="male_id" />
            </key>
            <one-to-many class="org.nescent.heliconius.hibernate.Crossexperiment" />
        </set>
        <set name="specimens" inverse="true">
            <key>
                <column name="individual_id" not-null="true" />
            </key>
            <one-to-many class="org.nescent.heliconius.hibernate.Specimen" />
        </set>
        <set name="individualprops" inverse="true">
            <key>
                <column name="individual_id" not-null="true" />
            </key>
            <one-to-many class="org.nescent.heliconius.hibernate.Individualprop" />
        </set>
        <set name="crossexperimentsForFemaleId" inverse="true">
            <key>
                <column name="female_id" />
            </key>
            <one-to-many class="org.nescent.heliconius.hibernate.Crossexperiment" />
        </set>
        <set name="individualImages" inverse="true">
            <key>
                <column name="individual_id" not-null="true" />
            </key>
            <one-to-many class="org.nescent.heliconius.hibernate.IndividualImage" />
        </set>
    </class>
</hibernate-mapping>
